Encoder/src/crc32.sv
`default_nettype none
`timescale 1ns / 1ps

`define LAGGING_SHIFT_IN (caxiod[30] ^ axiid[1])
`define LEADING_SHIFT_IN (caxiod[31] ^ axiid[0])
`define DOUBLED_SHIFT_IN (`LEADING_SHIFT_IN ^ `LAGGING_SHIFT_IN)

`define LAGGING_TAPS 4, 7, 10, 16, 22, 26
`define DOUBLED_TAPS 2, 5, 8, 11, 12, 23
`define LEADING_TAPS 3, 6, 9, 13, 17, 24, 27

/* this module implements CRC32-BZIP2, with a two bit input:
 *	- poly 0x04C11DB7
 *	- init 0xFFFFFFFF
 *	- NEW: XOR outputs
 *
 *	== check: 0xfc891918 ==
 *
 * this is the ethernet checksum!!
 */

module crc32(clk, rst, axiiv, axiid, axiov, axiod);

	/* old style i/o declaration, for clarity.
	 * easier on 80-char line limits...
	 * use this if you want, we don't care
	 */
	input logic clk, rst;

	input logic axiiv;
	input logic[1:0] axiid;

	output logic axiov;
	output logic[31:0] axiod;

	logic[31:0] caxiod, saxiod;
	integer i;

	assign axiov = 1;
	assign axiod = ~caxiod;

	always @(*) begin
		for (i = 0; i < 32; i = i + 1) begin
			case (i)
			0: saxiod[i] = `LAGGING_SHIFT_IN;
			1: saxiod[i] = `DOUBLED_SHIFT_IN;

			`LAGGING_TAPS:
				saxiod[i] = caxiod[i - 2] ^ `LAGGING_SHIFT_IN;
			`DOUBLED_TAPS:
				saxiod[i] = caxiod[i - 2] ^ `DOUBLED_SHIFT_IN;
			`LEADING_TAPS:
				saxiod[i] = caxiod[i - 2] ^ `LEADING_SHIFT_IN;

			default: saxiod[i] = caxiod[i - 2];
			endcase
		end
	end

	always @(posedge clk) begin
		if (rst) caxiod <= 32'hFFFF_FFFF;

		/* our output validity hinges on whether
		 * we are calculating anything or not
		 * on this clock cycle. if there is no
		 * valid input for us, don't do a shift
	 	 * this cycle
		 */
		else caxiod <= (axiiv) ? saxiod : caxiod;
	end

endmodule

`default_nettype wire

Encoder/src/ethernet_packager/fcs_gen.sv
`default_nettype none
`timescale 1ns / 1ps

// This module takes in input data and computes the FCS, which is generated
// by running CRC32-BZIP2 over the entirety of the input data. Data comes
// in dibits: MSB, MSb. 

module fcs_gen (
    input wire clk, rst, axiiv,
    input wire [1:0] axiid,
    output logic [31:0] cksum,
    output logic axiov
);

    logic crc_rst, crc_done, prev_axiiv;
    logic [31:0] fcs;
    assign crc_rst = ((rst) || ((prev_axiiv && ~axiiv) && ~rst));

    crc32 fcs_gen (
        .clk(clk), 
        .rst(crc_rst), 
        .axiiv(axiiv), 
        .axiid(axiid), 
        .axiov(crc_done), 
        .axiod(fcs));

    always_ff @(posedge clk) begin
        if (rst) begin
            axiov <= 1'b0;
            prev_axiiv <= 0;
        end else begin
            prev_axiiv <= axiiv; 
        end
      
        if ((~prev_axiiv && axiiv) && ~rst) begin
            axiov <= 1'b0;
        end
        
        if ((prev_axiiv && ~axiiv) && ~rst) begin
            axiov <= 1'b1;
            cksum <= fcs; 
        end
    end
endmodule

`default_nettype wire

Encoder/sim/ethernet_tb/fcs_gen_tb.sv
`timescale 1ns / 1ps
`default_nettype none

module fcs_gen_tb();
    logic clk, rst, axiiv, axiov;
    logic [31:0] cksum;
    logic[1:0] axiid, axiod;
    logic [167:0] msg; 
    assign msg = 168'h4261_7272_7921_2042_7265_616b_6661_7374_2074_696d65;

    fcs_gen uut (
        .clk(clk), 
        .rst(rst), 
        .axiiv(axiiv),
        .axiid(axiid),
        .cksum(cksum),
        .axiov(axiov));

    always begin
        #10;  
        clk = !clk;
    end

    initial begin

        $dumpfile("fcs_gen.vcd");
        $dumpvars(0, fcs_gen_tb);

        clk = 1;
        #20;
        rst = 1'b1;
        axiiv = 1'b1;
        #20;
        rst = 1'b0;
        axiiv = 1'b0;
        #20;
        for (int i = 0; i < 84; i = i + 1) begin
            axiid = {msg[167-2*i-1], msg[167-2*i]};
            axiiv = 1'b1;
            $display("%b           %b        %b       %d", axiiv, axiid, axiov, cksum); 
            #20;
        end
        #20;
        axiiv = 1'b0;
        #60;
        axiiv = 1'b1;
        $display("%b           %b        %b       %d", axiiv, axiid, axiov, cksum); 
        #200;

        $display("Finishing sim"); 
        $finish;
    end
endmodule

`default_nettype wire

Encoder/src/fcs_gen.vcd
$date
	Mon Nov  7 21:59:01 2022
$end
$version
	Icarus Verilog
$end
$timescale
	1ps
$end
$scope module fcs_gen_tb $end
$var wire 168 ! msg [167:0] $end
$var wire 32 " cksum [31:0] $end
$var wire 1 # axiov $end
$var reg 2 $ axiid [1:0] $end
$var reg 1 % axiiv $end
$var reg 1 & clk $end
$var reg 1 ' rst $end
$scope module uut $end
$var wire 2 ( axiid [1:0] $end
$var wire 1 % axiiv $end
$var wire 1 & clk $end
$var wire 1 ) crc_done $end
$var wire 1 * crc_rst $end
$var wire 1 ' rst $end
$var wire 32 + fcs [31:0] $end
$var reg 1 # axiov $end
$var reg 32 , cksum [31:0] $end
$var reg 1 - prev_axiiv $end
$scope module fcs_gen $end
$var wire 2 . axiid [1:0] $end
$var wire 1 % axiiv $end
$var wire 32 / axiod [31:0] $end
$var wire 1 ) axiov $end
$var wire 1 & clk $end
$var wire 1 * rst $end
$var reg 32 0 caxiod [31:0] $end
$var reg 32 1 saxiod [31:0] $end
$var integer 32 2 i [31:0] $end
$upscope $end
$upscope $end
$scope begin $ivl_for_loop0 $end
$var integer 32 3 i [31:0] $end
$upscope $end
$upscope $end
$enddefinitions $end
#0
$dumpvars
b0 3
bx 2
bx 1
bx 0
bx /
bx .
x-
bx ,
bx +
x*
1)
bx (
x'
1&
x%
bx $
x#
bx "
b10000100110000101110010011100100111100100100001001000000100001001110010011001010110000101101011011001100110000101110011011101000010000001110100011010010110110101100101 !
$end
#10000
0&
#20000
b1111xx1xxx1111xx11xxxxxxxxxxxxxx 1
b100000 2
b0 +
b0 /
0-
0#
b11111111111111111111111111111111 0
1*
1&
1%
1'
#30000
0&
#40000
0*
1&
0%
0'
#50000
0&
#60000
b1001100000100011101101101101 +
b1001100000100011101101101101 /
1-
b11110110011111011100010010010010 0
b11010000011101010010100100100110 1
b100000 2
1&
1%
b10 $
b10 (
b10 .
#70000
0&
#80000
b101011010010111100101101101110 +
b101011010010111100101101101110 /
b11010100101101000011010010010001 0
b1011111100100111111010010011101 1
b100000 2
1&
b0 $
b0 (
b0 .
b1 3
#90000
0&
#100000
b1111010100011101100111111000011 1
b100000 2
b10100000011011000000101101100010 +
b10100000011011000000101101100010 /
b1011111100100111111010010011101 0
1&
b10 3
#110000
0&
#120000
b10001100111100110000101101010010 +
b10001100111100110000101101010010 /
b1110011000011001111010010101101 0
b11000001011100001111010001101101 1
b100000 2
1&
b1 $
b1 (
b1 .
b11 3
#130000
0&
#140000
b110011110011000010110101001011 +
b110011110011000010110101001011 /
b11001100001100111101001010110100 0
b111001010011010111000110111110 1
b100000 2
1&
b10 $
b10 (
b10 .
b100 3
#150000
0&
#160000
b11001011111100011010100010011000 +
b11001011111100011010100010011000 /
b110100000011100101011101100111 0
b11011001101110110110011011110010 1
b100000 2
1&
b1 $
b1 (
b1 .
b101 3
#170000
0&
#180000
b101111110001101010001001100011 +
b101111110001101010001001100011 /
b11010000001110010101110110011100 0
b1001101101001100101000010101001 1
b100000 2
1&
b0 $
b0 (
b0 .
b110 3
#190000
0&
#200000
b10110110100110001011001011100001 +
b10110110100110001011001011100001 /
b1001001011001110100110100011110 0
b100101100111010011010001111000 1
b100000 2
1&
b10 $
b10 (
b10 .
b111 3
#210000
0&
#220000
b10010010101101011100110001010111 1
b100000 2
b11011010011000101100101110000111 +
b11011010011000101100101110000111 /
b100101100111010011010001111000 0
1&
b1000 3
#230000
0&
#240000
b1100100110010000000100011000110 +
b1100100110010000000100011000110 /
b10011011001101111111011100111001 0
b1101000000111101100000101010011 1
b100000 2
1&
b11 $
b11 (
b11 .
b1001 3
#250000
0&
#260000
b10011010101000100001100001110101 +
b10011010101000100001100001110101 /
b1100101010111011110011110001010 0
b10010001101101101000001110011111 1
b100000 2
1&
b0 $
b0 (
b0 .
b1010 3
#270000
0&
#280000
b1100111110010110100011100001110 +
b1100111110010110100011100001110 /
b10011000001101001011100011110001 0
b1100000110100101110001111000100 1
b100000 2
1&
b1 $
b1 (
b1 .
b1011 3
#290000
0&
#300000
b10010010011011100011101011100010 +
b10010010011011100011101011100010 /
b1101101100100011100010100011101 0
b10110110010001110001010001110100 1
b100000 2
1&
b10 $
b10 (
b10 .
b1100 3
#310000
0&
#320000
b1000000001110101101000011100101 +
b1000000001110101101000011100101 /
b10111111110001010010111100011010 0
b11111011110101011010000111011111 1
b100000 2
1&
b11 $
b11 (
b11 .
b1101 3
#330000
0&
#340000
b1001011010010111100011111001 +
b1001011010010111100011111001 /
b11110110100101101000011100000110 0
b11010111000110010011101011000001 1
b100000 2
1&
b0 $
b0 (
b0 .
b1110 3
#350000
0&
#360000
b100001011001001111111001010000 +
b100001011001001111111001010000 /
b11011110100110110000000110101111 0
b1111110101011010001101100001011 1
b100000 2
1&
b1 $
b1 (
b1 .
b1111 3
#370000
0&
#380000
b10001100000100011100001000101101 +
b10001100000100011100001000101101 /
b1110011111011100011110111010010 0
b11001111101110001111011101001000 1
b100000 2
1&
b10 $
b10 (
b10 .
b10000 3
#390000
0&
#400000
b111001110001010011001111011001 +
b111001110001010011001111011001 /
b11000110001110101100110000100110 0
b11000111010110011000010011000 1
b100000 2
1&
b11 $
b11 (
b11 .
b10001 3
#410000
0&
#420000
b11100011110101011101001011010000 +
b11100011110101011101001011010000 /
b11100001010100010110100101111 0
b1111001001010101000111111010010 1
b100000 2
1&
b1 $
b1 (
b1 .
b10010 3
#430000
0&
#440000
b10001011100101100101011011110100 +
b10001011100101100101011011110100 /
b1110100011010011010100100001011 0
b11010001101001101010010000101100 1
b100000 2
1&
b10 $
b10 (
b10 .
b10011 3
#450000
0&
#460000
b101010100110000100011001100100 +
b101010100110000100011001100100 /
b11010101011001111011100110011011 0
b1011000110111011100000010110101 1
b100000 2
1&
b0 $
b0 (
b0 .
b10100 3
#470000
0&
#480000
b10101110101000000000010000100100 +
b10101110101000000000010000100100 /
b1010001010111111111101111011011 0
b1001000001111001100100110110101 1
b100000 2
1&
b1 $
b1 (
b1 .
b10101 3
#490000
0&
#500000
b10111110010000010000110100100100 +
b10111110010000010000110100100100 /
b1000001101111101111001011011011 0
b10001110101101011011011011 1
b100000 2
1&
b0 $
b0 (
b0 .
b10110 3
#510000
0&
#520000
b11111001000001000011010010010011 +
b11111001000001000011010010010011 /
b110111110111100101101101100 0
b11111001011100011000000000111 1
b100000 2
1&
b10 $
b10 (
b10 .
b10111 3
#530000
0&
#540000
b11100100000100001101001001001111 +
b11100100000100001101001001001111 /
b11011111011110010110110110000 0
b1101111101111001011011011000000 1
b100000 2
1&
b0 $
b0 (
b0 .
b11000 3
#550000
0&
#560000
b10011001110000010111001001010001 +
b10011001110000010111001001010001 /
b1100110001111101000110110101110 0
b10010101101110010001000001100001 1
b100000 2
1&
b1 $
b1 (
b1 .
b11001 3
#570000
0&
#580000
b1100011110001001101010011110000 +
b1100011110001001101010011110000 /
b10011100001110110010101100001111 0
b1111001011011101001011101010010 1
b100000 2
1&
b0 $
b0 (
b0 .
b11010 3
#590000
0&
#600000
b11100001011110110100000011111111 1
b100000 2
b10000110100100010110100010101101 +
b10000110100100010110100010101101 /
b1111001011011101001011101010010 0
1&
b11011 3
#610000
0&
#620000
b11010010001011010001010110111 +
b11010010001011010001010110111 /
b11100101101110100101110101001000 0
b10011111011010110100111001001110 1
b100000 2
1&
b10 $
b10 (
b10 .
b11100 3
#630000
0&
#640000
b1100100010101011010110000000110 +
b1100100010101011010110000000110 /
b10011011101010100101001111111001 0
b1100111001010110111010010001010 1
b100000 2
1&
b0 $
b0 (
b0 .
b11101 3
#650000
0&
#660000
b10011000011011001100111110011111 1
b100000 2
b10011000110101001000101101110101 +
b10011000110101001000101101110101 /
b1100111001010110111010010001010 0
1&
b11110 3
#670000
0&
#680000
b1101110000100010000101100001110 +
b1101110000100010000101100001110 /
b10010001111011101111010011110001 0
b1000111101110111101001111000100 1
b100000 2
1&
b1 $
b1 (
b1 .
b11111 3
#690000
0&
#700000
b10110101000001110000101011100010 +
b10110101000001110000101011100010 /
b1001010111110001111010100011101 0
b101011111000111101010001110100 1
b100000 2
1&
b10 $
b10 (
b10 .
b100000 3
#710000
0&
#720000
b11011101100111100001000011100101 +
b11011101100111100001000011100101 /
b100010011000011110111100011010 0
b10000100110001001001101010110001 1
b100000 2
1&
b11 $
b11 (
b11 .
b100001 3
#730000
0&
#740000
b1110110011110000100001110010111 +
b1110110011110000100001110010111 /
b10001001100001111011110001101000 0
b101111100111001100101011001110 1
b100000 2
1&
b0 $
b0 (
b0 .
b100010 3
#750000
0&
#760000
b11011001111000010000111001011111 +
b11011001111000010000111001011111 /
b100110000111101111000110100000 0
b10010001111110011111110111101110 1
b100000 2
1&
b1 $
b1 (
b1 .
b100011 3
#770000
0&
#780000
b1100011010001010010010011001000 +
b1100011010001010010010011001000 /
b10011100101110101101101100110111 0
b1111111101010000100101000000101 1
b100000 2
1&
b10 $
b10 (
b10 .
b100100 3
#790000
0&
#800000
b10001101000101001001001100100011 +
b10001101000101001001001100100011 /
b1110010111010110110110011011100 0
b11000110111011101001010110101001 1
b100000 2
1&
b1 $
b1 (
b1 .
b100101 3
#810000
0&
#820000
b110100010100100100110010001111 +
b110100010100100100110010001111 /
b11001011101011011011001101110000 0
b100111001101001111011010101110 1
b100000 2
1&
b10 $
b10 (
b10 .
b100110 3
#830000
0&
#840000
b10011000000100101100011100001111 1
b100000 2
b11011000110010110000100101010001 +
b11011000110010110000100101010001 /
b100111001101001111011010101110 0
1&
b100111 3
#850000
0&
#860000
b1101101000010000011101011100101 1
b100000 2
b1100111111011010011100011110000 +
b1100111111011010011100011110000 /
b10011000000100101100011100001111 0
1&
b101000 3
#870000
0&
#880000
b10011111101101001110001111000011 +
b10011111101101001110001111000011 /
b1100000010010110001110000111100 0
b10001100011011110101011000101001 1
b100000 2
1&
b1 $
b1 (
b1 .
b101001 3
#890000
0&
#900000
b1111010000100101001001010111000 +
b1111010000100101001001010111000 /
b10000101111011010110110101000111 0
b11110001101111000111001110010 1
b100000 2
1&
b0 $
b0 (
b0 .
b101010 3
#910000
0&
#920000
b11100101000010010110110000111010 +
b11100101000010010110110000111010 /
b11010111101101001001111000101 0
b1101111000110110101001010100011 1
b100000 2
1&
b10 $
b10 (
b10 .
b101011 3
#930000
0&
#940000
b10111100011011010100101010001100 1
b100000 2
b10010000111001001010110101011100 +
b10010000111001001010110101011100 /
b1101111000110110101001010100011 0
1&
b101100 3
#950000
0&
#960000
b1001110110100011001001110101010 +
b1001110110100011001001110101010 /
b10110001001011100110110001010101 0
b11000100101110011011000101010100 1
b100000 2
1&
b1 $
b1 (
b1 .
b101101 3
#970000
0&
#980000
b10110001001111101100011100111 1
b100000 2
b111011010001100100111010101011 +
b111011010001100100111010101011 /
b11000100101110011011000101010100 0
1&
b101110 3
#990000
0&
#1000000
b11101101000110010011101010101111 +
b11101101000110010011101010101111 /
b10010111001101100010101010000 0
b1000110110110000011001110011001 1
b100000 2
1&
b11 $
b11 (
b11 .
b101111 3
#1010000
0&
#1020000
b10110000101001011111011100001000 +
b10110000101001011111011100001000 /
b1001111010110100000100011110111 0
b111101011010000010001111011100 1
b100000 2
1&
b10 $
b10 (
b10 .
b110000 3
#1030000
0&
#1040000
b11001111110101001111101011111010 +
b11001111110101001111101011111010 /
b110000001010110000010100000101 0
b11001001001011100010111101111010 1
b100000 2
1&
b1 $
b1 (
b1 .
b110001 3
#1050000
0&
#1060000
b111011100100101111011001011100 +
b111011100100101111011001011100 /
b11000100011011010000100110100011 0
b11000001101100001110111100010 1
b100000 2
1&
b10 $
b10 (
b10 .
b110010 3
#1070000
0&
#1080000
b11101010100010101100010011000100 +
b11101010100010101100010011000100 /
b10101011101010011101100111011 0
b1011100010101101101011110000010 1
b100000 2
1&
b1 $
b1 (
b1 .
b110011 3
#1090000
0&
#1100000
b10101110111010100000111010100100 +
b10101110111010100000111010100100 /
b1010001000101011111000101011011 0
b1000100010101111100010101101100 1
b100000 2
1&
b10 $
b10 (
b10 .
b110100 3
#1110000
0&
#1120000
b10110110111010110001110001001010 +
b10110110111010110001110001001010 /
b1001001000101001110001110110101 0
b101001000100001010100000001101 1
b100000 2
1&
b1 $
b1 (
b1 .
b110101 3
#1130000
0&
#1140000
b11011111011011010110110010011100 +
b11011111011011010110110010011100 /
b100000100100101001001101100011 0
b10000010010010100100110110001100 1
b100000 2
1&
b0 $
b0 (
b0 .
b110110 3
#1150000
0&
#1160000
b1111001011101001010111111000100 +
b1111001011101001010111111000100 /
b10000110100010110101000000111011 0
b10111011011100110011000110101 1
b100000 2
1&
b10 $
b10 (
b10 .
b110111 3
#1170000
0&
#1180000
b1011001011110001000010101100011 1
b100000 2
b11101000100100011001100111001010 +
b11101000100100011001100111001010 /
b10111011011100110011000110101 0
1&
b111000 3
#1190000
0&
#1200000
b10101111000001010100000111110010 +
b10101111000001010100000111110010 /
b1010000111110101011111000001101 0
b1001010011010001100001101011010 1
b100000 2
1&
b11 $
b11 (
b11 .
b111001 3
#1210000
0&
#1220000
b10111000110101000001101001111100 +
b10111000110101000001101001111100 /
b1000111001010111110010110000011 0
b11000011011101000101110111011 1
b100000 2
1&
b0 $
b0 (
b0 .
b111010 3
#1230000
0&
#1240000
b11101010110100100101001010011101 +
b11101010110100100101001010011101 /
b10101001011011010110101100010 0
b1011001111101011001001101010001 1
b100000 2
1&
b11 $
b11 (
b11 .
b111011 3
#1250000
0&
#1260000
b10101111100010000101011111000000 +
b10101111100010000101011111000000 /
b1010000011101111010100000111111 0
b1000001110111101010000011111100 1
b100000 2
1&
b10 $
b10 (
b10 .
b111100 3
#1270000
0&
#1280000
b10110111101000110110010001101101 +
b10110111101000110110010001101101 /
b1001000010111001001101110010010 0
b101000111100000101010100100110 1
b100000 2
1&
b11 $
b11 (
b11 .
b111101 3
#1290000
0&
#1300000
b11011110100011011001000110110111 +
b11011110100011011001000110110111 /
b100001011100100110111001001000 0
b10000001000010001010010010010111 1
b100000 2
1&
b10 $
b10 (
b10 .
b111110 3
#1310000
0&
#1320000
b1111010001101100100011011011111 +
b1111010001101100100011011011111 /
b10000101110010011011100100100000 0
b11110101001001101111111101110 1
b100000 2
1&
b0 $
b0 (
b0 .
b111111 3
#1330000
0&
#1340000
b1111010100100110111111110111000 1
b100000 2
b11100001010110110010000000010001 +
b11100001010110110010000000010001 /
b11110101001001101111111101110 0
1&
b1000000 3
#1350000
0&
#1360000
b10001100111011101011101100101001 +
b10001100111011101011101100101001 /
b1110011000100010100010011010110 0
b11000001000001100011010110000001 1
b100000 2
1&
b1 $
b1 (
b1 .
b1000001 3
#1370000
0&
#1380000
b110111011110111111000100010000 +
b110111011110111111000100010000 /
b11001000100001000000111011101111 0
b101111010100110001110101100101 1
b100000 2
1&
b0 $
b0 (
b0 .
b1000010 3
#1390000
0&
#1400000
b10111101010011000111010110010100 1
b100000 2
b11010000101011001110001010011010 +
b11010000101011001110001010011010 /
b101111010100110001110101100101 0
1&
b1000011 3
#1410000
0&
#1420000
b1000110011100101001011111011100 +
b1000110011100101001011111011100 /
b10111001100011010110100000100011 0
b11101011011101101000011001010101 1
b100000 2
1&
b10 $
b10 (
b10 .
b1000100 3
#1430000
0&
#1440000
b11101000010110100001011000100 +
b11101000010110100001011000100 /
b11100010111101001011110100111011 0
b10001011110100101111010011101100 1
b100000 2
1&
b11 $
b11 (
b11 .
b1000101 3
#1450000
0&
#1460000
b1111101101011110011000001111101 +
b1111101101011110011000001111101 /
b10000010010100001100111110000010 0
b100000000000001100011010001 1
b100000 2
1&
b10 $
b10 (
b10 .
b1000110 3
#1470000
0&
#1480000
b11111111001111101111101010011001 +
b11111111001111101111101010011001 /
b110000010000010101100110 0
b11000001000001010110011000 1
b100000 2
1&
b0 $
b0 (
b0 .
b1000111 3
#1490000
0&
#1500000
b11111000001110101111011111010000 +
b11111000001110101111011111010000 /
b111110001010000100000101111 0
b11011110101010011110100001011 1
b100000 2
1&
b10 $
b10 (
b10 .
b1001000 3
#1510000
0&
#1520000
b11101001011010011110010000101101 +
b11101001011010011110010000101101 /
b10110100101100001101111010010 0
b1010011110110100101010000100110 1
b100000 2
1&
b1 $
b1 (
b1 .
b1001001 3
#1530000
0&
#1540000
b1000010001010100111011001000001 1
b100000 2
b10101100001001011010101111011001 +
b10101100001001011010101111011001 /
b1010011110110100101010000100110 0
1&
b1001010 3
#1550000
0&
#1560000
b10110000100101101010111101100111 +
b10110000100101101010111101100111 /
b1001111011010010101000010011000 0
b111101101001010100001001100000 1
b100000 2
1&
b10 $
b10 (
b10 .
b1001011 3
#1570000
0&
#1580000
b11110010010101000001010000110111 1
b100000 2
b11000010010110101011110110011111 +
b11000010010110101011110110011111 /
b111101101001010100001001100000 0
1&
b1001100 3
#1590000
0&
#1600000
b111010001100110100010001 +
b111010001100110100010001 /
b11111111000101110011001011101110 0
b11111000100111011101011000001111 1
b100000 2
1&
b1 $
b1 (
b1 .
b1001101 3
#1610000
0&
#1620000
b11101000110011010001000111 +
b11101000110011010001000111 /
b11111100010111001100101110111000 0
b11110001011100110010111011100000 1
b100000 2
1&
b11 $
b11 (
b11 .
b1001110 3
#1630000
0&
#1640000
b111000011101110101001110001 +
b111000011101110101001110001 /
b11111000111100010001010110001110 0
b11101010010001100110110101010110 1
b100000 2
1&
b10 $
b10 (
b10 .
b1001111 3
#1650000
0&
#1660000
b10100000100110111000111000110110 1
b100000 2
b10101101110011001001010101001 +
b10101101110011001001010101001 /
b11101010010001100110110101010110 0
1&
b1010000 3
#1670000
0&
#1680000
b1010010001001110101011100010000 +
b1010010001001110101011100010000 /
b10101101110110001010100011101111 0
b10110111011000101010001110111100 1
b100000 2
1&
b1 $
b1 (
b1 .
b1010001 3
#1690000
0&
#1700000
b1000101110111100111101010011010 +
b1000101110111100111101010011010 /
b10111010001000011000010101100101 0
b11100101110001010011001101001101 1
b100000 2
1&
b10 $
b10 (
b10 .
b1010010 3
#1710000
0&
#1720000
b10011110100101101111011001011010 1
b100000 2
b11010001110101100110010110010 +
b11010001110101100110010110010 /
b11100101110001010011001101001101 0
1&
b1010011 3
#1730000
0&
#1740000
b1110111000110001111111110110001 1
b100000 2
b1100001011010010000100110100101 +
b1100001011010010000100110100101 /
b10011110100101101111011001011010 0
1&
b1010100 3
#1750000
0&
#1760000
b1100001011010010000100110100101 "
b1100001011010010000100110100101 ,
1#
0-
0*
1&
0%
#1770000
0&
#1780000
1&
#1790000
0&
#1800000
1&
#1810000
0&
#1820000
b11011100011000111111111011000100 1
b100000 2
b10001000111001110000000001001110 +
b10001000111001110000000001001110 /
0#
1-
b1110111000110001111111110110001 0
1&
1%
#1830000
0&
#1840000
b1111000000011011100000001111110 1
b100000 2
b100011100111000000000100111011 +
b100011100111000000000100111011 /
b11011100011000111111111011000100 0
1&
#1850000
0&
#1860000
b11100000001101110000000111111000 1
b100000 2
b10000111111100100011111110000001 +
b10000111111100100011111110000001 /
b1111000000011011100000001111110 0
1&
#1870000
0&
#1880000
b10001001010111100011110010001110 1
b100000 2
b11111110010001111111000000111 +
b11111110010001111111000000111 /
b11100000001101110000000111111000 0
1&
#1890000
0&
#1900000
b101000001110111101010011100001 1
b100000 2
b1110110101000011100001101110001 +
b1110110101000011100001101110001 /
b10001001010111100011110010001110 0
1&
#1910000
0&
#1920000
b10100100001011100100111000110011 1
b100000 2
b11010111110001000010101100011110 +
b11010111110001000010101100011110 /
b101000001110111101010011100001 0
1&
#1930000
0&
#1940000
b10011101111110100001111000010101 1
b100000 2
b1011011110100011011000111001100 +
b1011011110100011011000111001100 /
b10100100001011100100111000110011 0
1&
#1950000
0&
#1960000
b1111010101010110101111010001101 1
b100000 2
b1100010000001011110000111101010 +
b1100010000001011110000111101010 /
b10011101111110100001111000010101 0
1&
#1970000
0&
#1980000
b11101010101011010111101000110100 1
b100000 2
b10000101010101001010000101110010 +
b10000101010101001010000101110010 /
b1111010101010110101111010001101 0
1&
#1990000
0&
#2000000
b10100011001101111101001110111110 1
b100000 2
b10101010100101000010111001011 +
b10101010100101000010111001011 /
b11101010101011010111101000110100 0
1&
#2010000
0&
#2020000
b10000001100111000110100000100001 1
b100000 2
b1011100110010000010110001000001 +
b1011100110010000010110001000001 /
b10100011001101111101001110111110 0
1&
